factorygame/__init__.py
factorygame/factory_engine.py
factorygame/core/__init__.py
factorygame/core/blueprint.py
factorygame/core/engine_base.py
factorygame/core/input_base.py
factorygame/core/input_tk.py
factorygame/utils/__init__.py
factorygame/utils/gameplay.py
factorygame/utils/loc.py
factorygame/utils/mymath.py
factorygame/utils/tkutils.py
factorygame/utils/fmt/__init__.py
factorygame/utils/fmt/case_swap.py
test/__init__.py
test/core/__init__.py
test/core/blueprint_test.py
test/core/engine_test.py
test/core/input_test.py
test/template/__init__.py
test/template/template_gui.py
test/utils/__init__.py
test/utils/tkutils_test.py
factorygame_dave22153-0.2.0.dist-info/LICENSE
factorygame_dave22153-0.2.0.dist-info/METADATA
factorygame_dave22153-0.2.0.dist-info/WHEEL
factorygame_dave22153-0.2.0.dist-info/top_level.txt
factorygame_dave22153-0.2.0.dist-info/RECORD
