Metadata-Version: 2.1
Name: factorygame-dave22153
Version: 0.2.0
Summary: Python game engine to have a 2d movable "graph".
Home-page: https://gitlab.com/factorygame/factorygame
Author: Dave22153
Author-email: dkanekanian@gmail.com
License: UNKNOWN
Platform: UNKNOWN
Classifier: Programming Language :: Python :: 3
Classifier: License :: OSI Approved :: MIT License
Classifier: Operating System :: OS Independent
Requires-Python: >=3.2
